MANIFEST.in
README.md
setup.cfg
setup.py
src/slack_bang/README.md
src/slack_bang/__init__.py
src/slack_bang/bang.py
src/slack_bang/bang_web.py
src/slack_bang/cli.py
src/slack_bang/dist-requirements.txt
src/slack_bang/requirements.txt
src/slack_bang/services.py
src/slack_bang.egg-info/PKG-INFO
src/slack_bang.egg-info/SOURCES.txt
src/slack_bang.egg-info/dependency_links.txt
src/slack_bang.egg-info/entry_points.txt
src/slack_bang.egg-info/requires.txt
src/slack_bang.egg-info/top_level.txt