Metadata-Version: 1.1
Name: slack-bang
Version: 0.1.2
Summary: Send message to slack webhook
Home-page: https://git.dglecom.net/projects/OPS/repos/slack_bang/browse
Author: Ross Crawford-d'Heureuse
Author-email: r.crawford@douglas.de
License: MIT License
Platform: UNKNOWN
Classifier: Environment :: Web Environment
Classifier: Programming Language :: Python
Classifier: Programming Language :: Python :: 2.7
Classifier: Topic :: Internet :: WWW/HTTP
Classifier: Topic :: Internet :: WWW/HTTP :: Dynamic Content
